conn_check_configs-1.0.11.dist-info/WHEEL
conn_check_configs-1.0.11.dist-info/top_level.txt
conn_check_configs-1.0.11.dist-info/METADATA
conn_check_configs-1.0.11.dist-info/RECORD
conn_check_configs-1.0.11.dist-info/metadata.json
conn_check_configs-1.0.11.dist-info/DESCRIPTION.rst
conn_check_configs-1.0.11.dist-info/entry_points.txt
conn_check_configs/django.py
conn_check_configs/__init__.py
conn_check_configs/version.txt
