Metadata-Version: 2.0
Name: conn-check-configs
Version: 1.0.11
Summary: Utilities for generating conn-check YAML configs from other sources, such as Django settings
Home-page: https://launchpad.net/conn-check
Author: James Westby, Wes Mason
Author-email: james.westby@canonical.com, wesley.mason@canonical.com
License: LGPL3
Platform: UNKNOWN
Classifier: Topic :: System :: Networking
Classifier: Development Status :: 4 - Beta
Classifier: Programming Language :: Python
Classifier: Intended Audience :: Developers
Classifier: Operating System :: OS Independent
Classifier: Intended Audience :: System Administrators
Classifier: License :: OSI Approved :: GNU General Public License v3 (GPLv3)
Requires-Dist: pyyaml
